odoo/addons/stock_package_type_button_box/README.rst
odoo/addons/stock_package_type_button_box/__init__.py
odoo/addons/stock_package_type_button_box/__manifest__.py
odoo/addons/stock_package_type_button_box/i18n/stock_package_type_button_box.pot
odoo/addons/stock_package_type_button_box/readme/CONTRIBUTORS.rst
odoo/addons/stock_package_type_button_box/readme/DESCRIPTION.rst
odoo/addons/stock_package_type_button_box/static/description/icon.png
odoo/addons/stock_package_type_button_box/static/description/index.html
odoo/addons/stock_package_type_button_box/views/stock_package_type.xml
odoo_addon_stock_package_type_button_box-16.0.1.0.0.2.dist-info/METADATA
odoo_addon_stock_package_type_button_box-16.0.1.0.0.2.dist-info/WHEEL
odoo_addon_stock_package_type_button_box-16.0.1.0.0.2.dist-info/top_level.txt
odoo_addon_stock_package_type_button_box-16.0.1.0.0.2.dist-info/RECORD
