Metadata-Version: 2.1
Name: odoo-addon-stock-package-type-button-box
Version: 16.0.1.0.0.2
Summary: This module is a technical module that allows to fill in a button box for Stock Package Type form view
Home-page: https://github.com/OCA/stock-logistics-warehouse
Author: ACSONE SA/NV,Odoo Community Association (OCA)
Author-email: support@odoo-community.org
License: AGPL-3
Platform: UNKNOWN
Classifier: Programming Language :: Python
Classifier: Framework :: Odoo
Classifier: Framework :: Odoo :: 16.0
Classifier: License :: OSI Approved :: GNU Affero General Public License v3
Requires-Python: >=3.10
Requires-Dist: odoo (<16.1dev,>=16.0a)
